jokekappa/__init__.py
jokekappa/core.py
jokekappa/jokes/codetengu_weekly.json
jokekappa/jokes/kobeengineer.json
jokekappa/jokes/others.json
jokekappa/jokes/pyjokes.json
jokekappa-0.1.9.data/scripts/jokekappa
jokekappa-0.1.9.dist-info/METADATA
jokekappa-0.1.9.dist-info/RECORD
jokekappa-0.1.9.dist-info/WHEEL
jokekappa-0.1.9.dist-info/top_level.txt
